[
  {
    "id": "ss_001",
    "text": "精神保健福祉法に基づき、自傷他害の恐れがある場合に、都道府県知事の権限で行われる入院形態はどれか。",
    "options": ["任意入院", "医療保護入院", "措置入院", "応急入院"],
    "correctIndex": 2,
    "explanation": "措置入院は、自分を傷つけたり他人に害を及ぼしたりする恐れがある場合に、行政の責任において強制的に行われる入院です。",
    "subject": "legal_system"
  },
  {
    "id": "ss_002",
    "text": "精神保健福祉法における「医療保護入院」に必要な要件として、正しいのはどれか。",
    "options": ["本人の同意", "家族等のうちいずれかの者の同意と精神保健指定医の診察", "警察署長の許可", "裁判所の命令"],
    "correctIndex": 1,
    "explanation": "医療保護入院は、本人の同意が得られない場合に、家族等の同意と指定医の判断により行われます。",
    "subject": "legal_system"
  },
  {
    "id": "ss_003",
    "text": "障害者総合支援法における「自立支援医療（精神通院医療）」の原則的な自己負担割合はどれか。",
    "options": ["1割", "2割", "3割", "無料"],
    "correctIndex": 0,
    "explanation": "自立支援医療制度を利用すると、精神科の通院や薬代の自己負担は原則1割に軽減されます（所得に応じた上限額あり）。",
    "subject": "medical_support"
  },
  {
    "id": "ss_004",
    "text": "精神障害者保健福祉手帳の等級は何段階に分かれているか。",
    "options": ["1級〜2級", "1級〜3級", "1級〜4級", "1級〜6級"],
    "correctIndex": 1,
    "explanation": "精神障害者保健福祉手帳は、障害の程度により1級（重度）から3級までの3段階があります。",
    "subject": "certificate"
  },
  {
    "id": "ss_005",
    "text": "障害者総合支援法のサービスのうち、一般企業への就職を希望する人に対して、一定期間、訓練や就職活動支援を行うのはどれか。",
    "options": ["就労継続支援A型", "就労継続支援B型", "就労移行支援", "自立訓練"],
    "correctIndex": 2,
    "explanation": "就労移行支援は、一般就労を目指す人に対し、最長2年間の期限でトレーニングや求職活動のサポートを提供します。",
    "subject": "employment_support"
  },
  {
    "id": "ss_006",
    "text": "精神障害者が障害年金を受給するために、原則として必要な条件（初診日要件等以外）はどれか。",
    "options": ["働いていないこと", "一定の障害の状態にあること", "独り暮らしであること", "65歳以上であること"],
    "correctIndex": 1,
    "explanation": "障害年金は、病気やケガによって生活や仕事に制限がある場合に支給されます。就労していても程度に応じて受給可能です。",
    "subject": "pension"
  },
  {
    "id": "ss_007",
    "text": "成年後見制度において、本人の判断能力が十分なうちに、将来に備えてあらかじめ後見人を決めておく制度を何と呼ぶか。",
    "options": ["法定後見制度", "任意後見制度", "日常生活自立支援事業", "権利擁護事業"],
    "correctIndex": 1,
    "explanation": "任意後見制度は、本人があらかじめ信頼できる人と契約を結んでおく制度です。法定後見は判断能力が低下した後に申し立てます。",
    "subject": "guardianship"
  },
  {
    "id": "ss_008",
    "text": "生活保護法における「住宅扶助」の対象となる費用はどれか。",
    "options": ["食費", "家賃", "医療費", "葬祭費"],
    "correctIndex": 1,
    "explanation": "住宅扶助は、家賃や地代、補修費など、住まいを維持するために必要な費用を支給するものです。",
    "subject": "livelihood_protection"
  },
  {
    "id": "ss_009",
    "text": "2013年に施行された「障害者差別解消法」において、行政機関等に義務付けられ、民間事業者には努力義務（後に義務化）とされたものはどれか。",
    "options": ["一律のサービス提供", "合理的配慮の提供", "バリアフリー化の禁止", "全額無料化"],
    "correctIndex": 1,
    "explanation": "合理的配慮とは、障害のある人が直面する障壁を取り除くための必要かつ適切な変更や調整のことです。",
    "subject": "legal_rights"
  },
  {
    "id": "ss_010",
    "text": "精神保健福祉法に基づく「精神医療審査会」の主な役割はどれか。",
    "options": ["病院の経営改善", "入院の必要性や処遇の妥当性を審査すること", "新しい薬の承認", "医師の国家試験の実施"],
    "correctIndex": 1,
    "explanation": "精神医療審査会は、入院患者の権利を守るため、入院の要否や行動制限の妥当性を第三者の立場で審査する機関です。",
    "subject": "rights_protection"
  }
]
